ilcdlib/__init__.py
ilcdlib/__main__.py
ilcdlib/__version__.py
ilcdlib/cli.py
ilcdlib/common.py
ilcdlib/compat/__init__.py
ilcdlib/compat/pydantic.py
ilcdlib/const.py
ilcdlib/data/category_mapping/epdnorge.csv
ilcdlib/data/category_mapping/oekobaudat.csv
ilcdlib/data/ilcd_epd_ref.zip
ilcdlib/dto.py
ilcdlib/entity/__init__.py
ilcdlib/entity/base_scope_set_reader.py
ilcdlib/entity/category.py
ilcdlib/entity/compliance.py
ilcdlib/entity/contact.py
ilcdlib/entity/exchage.py
ilcdlib/entity/flow.py
ilcdlib/entity/lcia.py
ilcdlib/entity/material.py
ilcdlib/entity/pcr.py
ilcdlib/entity/source.py
ilcdlib/entity/unit.py
ilcdlib/entity/validation.py
ilcdlib/epd/__init__.py
ilcdlib/epd/cli.py
ilcdlib/epd/declaration_convertor.py
ilcdlib/epd/dialect/__init__.py
ilcdlib/epd/dialect/environdec.py
ilcdlib/epd/dialect/epddenmark.py
ilcdlib/epd/dialect/epditaly.py
ilcdlib/epd/dialect/epdnorge.py
ilcdlib/epd/dialect/indata.py
ilcdlib/epd/dialect/itb.py
ilcdlib/epd/dialect/oekobaudat.py
ilcdlib/epd/factory.py
ilcdlib/epd/reader.py
ilcdlib/extension.py
ilcdlib/http_common.py
ilcdlib/mapping/__init__.py
ilcdlib/mapping/category.py
ilcdlib/mapping/common.py
ilcdlib/mapping/compliance.py
ilcdlib/mapping/flows.py
ilcdlib/mapping/impacts.py
ilcdlib/mapping/indicators.py
ilcdlib/mapping/properties.py
ilcdlib/mapping/units.py
ilcdlib/medium/__init__.py
ilcdlib/medium/archive.py
ilcdlib/medium/soda4lca.py
ilcdlib/py.typed
ilcdlib/reference_data.py
ilcdlib/sanitizing/__init__.py
ilcdlib/sanitizing/domain.py
ilcdlib/sanitizing/phone.py
ilcdlib/sanitizing/text.py
ilcdlib/soda4lca/__init__.py
ilcdlib/soda4lca/api_client.py
ilcdlib/soda4lca/api_client_4x.py
ilcdlib/type.py
ilcdlib/utils.py
ilcdlib/xml_parser.py
ilcdlib-5.1.1.dist-info/LICENSE
ilcdlib-5.1.1.dist-info/METADATA
ilcdlib-5.1.1.dist-info/WHEEL
ilcdlib-5.1.1.dist-info/RECORD
