Metadata-Version: 2.3
Name: ilcdlib
Version: 5.1.1
Summary: A toolkit for reading and writing ILCD format and it's derivatives
License: Apache-2.0
Author: C-Change Labs
Author-email: support@c-change-labs.com
Maintainer: C-Change Labs
Maintainer-email: open-source@c-change-labs.com
Requires-Python: >=3.11,<4.0
Classifier: Development Status :: 3 - Alpha
Classifier: Intended Audience :: Developers
Classifier: License :: OSI Approved :: Apache Software License
Classifier: Operating System :: OS Independent
Classifier: Programming Language :: Python :: 3
Classifier: Programming Language :: Python :: 3.11
Classifier: Programming Language :: Python :: 3.12
Classifier: Programming Language :: Python :: 3.13
Classifier: Topic :: Software Development :: Libraries :: Python Modules
Requires-Dist: cli-rack (>=1.0.6)
Requires-Dist: lxml (>=4.9.2,<4.10.0)
Requires-Dist: openepd (>=7.0.1,<=8.0.0)
Requires-Dist: pydantic (>=2.0,<3)
Requires-Dist: pytz (>=2023.3)
Requires-Dist: requests (>=2.1.0,<3.0.0)
Requires-Dist: urllib3 (>=1.26.17,<3.0.0)
Project-URL: Repository, https://github.com/cchangelabs/ilcdlib
